synderm/__init__.py
synderm/fine_tune/__init__.py
synderm/fine_tune/inpaint_diffusion.py
synderm/fine_tune/text_to_image_diffusion.py
synderm/fine_tune/util.py
synderm/generation/__init__.py
synderm/generation/generate.py
synderm/generation/util.py
synderm/utils/__init__.py
synderm/utils/utils.py
synderm-0.1.4.dist-info/licenses/LICENSE
synderm-0.1.4.dist-info/METADATA
synderm-0.1.4.dist-info/WHEEL
synderm-0.1.4.dist-info/top_level.txt
synderm-0.1.4.dist-info/RECORD
