Metadata-Version: 2.4
Name: synderm
Version: 0.1.4
Summary: A package for generating synthetic data to augment image classifiers.
Author-email: Thomas Buckley <32546943+2v@users.noreply.github.com>
License: MIT
Project-URL: Homepage, https://github.com/manrai/synthetic-derm
Project-URL: Documentation, https://synthetic-derm.readthedocs.io/en/latest/index.html
Project-URL: Repository, https://github.com/manrai/synthetic-derm
Project-URL: Issues, https://github.com/manrai/synthetic-derm/issues
Keywords: synthetic data,image classification,diffusion models,data augmentation,dermatology,machine learning
Classifier: Development Status :: 3 - Alpha
Classifier: Intended Audience :: Science/Research
Classifier: Intended Audience :: Developers
Classifier: License :: OSI Approved :: MIT License
Classifier: Programming Language :: Python :: 3
Classifier: Programming Language :: Python :: 3.7
Classifier: Programming Language :: Python :: 3.8
Classifier: Programming Language :: Python :: 3.9
Classifier: Programming Language :: Python :: 3.10
Classifier: Programming Language :: Python :: 3.11
Classifier: Topic :: Scientific/Engineering :: Artificial Intelligence
Classifier: Topic :: Scientific/Engineering :: Image Recognition
Requires-Python: >=3.7
License-File: LICENSE
Requires-Dist: numpy>=1.18.0
Requires-Dist: requests>=2.25.1
Requires-Dist: torch>=1.7.1
Requires-Dist: diffusers>=0.7.2
Requires-Dist: Pillow>=8.0.0
Requires-Dist: torchvision>=0.8.1
Requires-Dist: tqdm>=4.50.0
Requires-Dist: accelerate>=0.12.0
Requires-Dist: datasets>=3.1.0
Requires-Dist: huggingface_hub>=0.26.2
Requires-Dist: lovely_tensors>=0.1.17
Requires-Dist: pandas>=1.0.0
Requires-Dist: rich>=13.0.0
Requires-Dist: transformers>=4.0.0
Requires-Dist: wandb>=0.19.0
Dynamic: license-file
